MANIFEST.in
README.rst
setup.cfg
setup.py
test-requirements.txt
testinstances/__init__.py
testinstances/exceptions.py
testinstances/managed_instance.py
testinstances/mongo_instance.py
testinstances/redis_instance.py
testinstances/utils.py
testinstances.egg-info/PKG-INFO
testinstances.egg-info/SOURCES.txt
testinstances.egg-info/dependency_links.txt
testinstances.egg-info/not-zip-safe
testinstances.egg-info/requires.txt
testinstances.egg-info/top_level.txt
tests/__init__.py
tests/conftest.py
tests/testinstances/__init__.py
tests/testinstances/test_managed_instance.py
tests/testinstances/test_mongo_instance.py
tests/testinstances/test_redis_instance.py