Metadata-Version: 1.0
Name: testinstances
Version: 0.3.0
Summary: Managed test instances for integration tests
Home-page: https://github.com/Parsely/testinstances
Author: Keith Bourgoin
Author-email: keith at parsely dot com
License: Apache License 2.0
Platform: UNKNOWN
